<?xml version="1.0" encoding="UTF-8"?>
<BRERuleListType xmlns="http://www.audatex.com/SAXIF">
 <Rule>
  <CountryOrganizationId>DE</CountryOrganizationId>
  <ItemId>D9B1C2DB-21AC-ADF6-8C8B-67D57E50DD36</ItemId>
  <Context>
   <Process>NO_PROCESS</Process>
   <ProcessStep>flsReassign</ProcessStep>
   <OrganizationId>RS_DE_SV_ALLIANZ_ADMIN</OrganizationId>
  </Context>
  <RuleType>FlowProcessorConfiguration</RuleType>
  <Key>ChangeTaskOwnerWorkflowFunction.FLSNotificationPostAction(1513588963780)</Key>
  <Value>{errorNotificationEMAILAddress:"michel.varga@ax-ao.de"}</Value>
  <Status>Active</Status>
  <CreatedBy>MM-P-C6CFD7A2</CreatedBy>
  <CreationTimeStamp>2017-12-18T10:23:15.607</CreationTimeStamp>
  <LastUpdatedBy>MM-P-C6CFD7A2</LastUpdatedBy>
  <LastUpdateTimeStamp>2018-01-15T13:23:20.582</LastUpdateTimeStamp>
 </Rule>
 <Rule>
  <CountryOrganizationId>DE</CountryOrganizationId>
  <ItemId>AE1C580B-21D7-17B9-A80E-47DCD7BD56CB</ItemId>
  <Context>
   <Process>NO_PROCESS</Process>
   <ProcessStep>flsReassign</ProcessStep>
   <OrganizationId>RS_DE_SV_ALLIANZ_ADMIN</OrganizationId>
  </Context>
  <RuleType>FlowProcessorConfiguration</RuleType>
  <Key>ChangeTaskOwnerWorkflowFunction.KADFlsPrintTransformation(1513588920633)</Key>
  <Value>{typeOfReport: "DISPATCH", deleteOldReport: "true"}
</Value>
  <Status>Active</Status>
  <CreatedBy>MM-P-C6CFD7A2</CreatedBy>
  <CreationTimeStamp>2017-12-18T10:23:07.260</CreationTimeStamp>
  <LastUpdatedBy>MM-P-C6CFD7A2</LastUpdatedBy>
  <LastUpdateTimeStamp>2017-12-18T10:23:07.260</LastUpdateTimeStamp>
 </Rule>
 <Rule>
  <CountryOrganizationId>DE</CountryOrganizationId>
  <ItemId>7EFDE039-3A08-A4CD-3397-A697C3042AF6</ItemId>
  <Context>
   <Process>NO_PROCESS</Process>
   <ProcessStep>WorkListGrid</ProcessStep>
   <OrganizationId>RS_DE_SV_ALLIANZ_ADMIN</OrganizationId>
  </Context>
  <RuleType>Configuration</RuleType>
  <Key>WorkListGrid.action.worklistgrid_closed</Key>
  <Value>ReopenTask,CopyIntoNewCase</Value>
  <Status>Active</Status>
  <CreatedBy>MM-P-9BBB2219</CreatedBy>
  <CreationTimeStamp>2017-04-13T15:20:07.782</CreationTimeStamp>
  <LastUpdatedBy>MM-P-C6CFD7A2</LastUpdatedBy>
  <LastUpdateTimeStamp>2017-11-22T20:18:25.263</LastUpdateTimeStamp>
 </Rule>
 <Rule>
  <CountryOrganizationId>DE</CountryOrganizationId>
  <ItemId>05B9131F-B2D3-7FB0-C64E-D954DB11EAD6</ItemId>
  <Context>
   <OrganizationId>RS_DE_SV_ALLIANZ_ADMIN</OrganizationId>
  </Context>
  <RuleType>DataAccessRight</RuleType>
  <Key>TaskType.COPY</Key>
  <Value>{"AccessLevel":"SPECIFIC","AccessLevelParam":["ML-O-209801"]}</Value>
  <Status>Active</Status>
  <CreatedBy>MM-P-9BBB2219</CreatedBy>
  <CreationTimeStamp>2017-04-13T15:20:07.199</CreationTimeStamp>
  <LastUpdatedBy>MM-P-C6CFD7A2</LastUpdatedBy>
  <LastUpdateTimeStamp>2017-12-18T10:29:54.953</LastUpdateTimeStamp>
 </Rule>
 <Rule>
  <CountryOrganizationId>DE</CountryOrganizationId>
  <ItemId>06DBA6BE-4710-9BD7-973D-1E01D0B78D4C</ItemId>
  <Context>
   <Process>NO_PROCESS</Process>
   <ProcessStep>DashBoard</ProcessStep>
   <OrganizationId>RS_DE_SV_ALLIANZ_ADMIN</OrganizationId>
  </Context>
  <RuleType>Configuration</RuleType>
  <Key>componentTemplate.root.dashboard</Key>
  <Value>MaterialDesignDashboard.htm</Value>
  <Status>Active</Status>
  <CreatedBy>MM-P-9BBB2219</CreatedBy>
  <CreationTimeStamp>2017-04-13T15:20:07.636</CreationTimeStamp>
  <LastUpdatedBy>MM-P-C6CFD7A2</LastUpdatedBy>
  <LastUpdateTimeStamp>2017-11-14T09:28:17.498</LastUpdateTimeStamp>
 </Rule>
 <Rule>
  <CountryOrganizationId>DE</CountryOrganizationId>
  <ItemId>B3BB841E-2A0A-6E1B-05F4-36F9CFAC245F</ItemId>
  <Context>
   <Process>NO_PROCESS</Process>
   <ProcessStep>MaterialGrid</ProcessStep>
   <OrganizationId>RS_DE_SV_ALLIANZ_ADMIN</OrganizationId>
  </Context>
  <RuleType>FieldVisibility</RuleType>
  <Key>worklistgrid_open</Key>
  <Value>show</Value>
  <Status>Active</Status>
  <CreatedBy>MM-P-9BBB2219</CreatedBy>
  <CreationTimeStamp>2017-04-13T15:20:07.391</CreationTimeStamp>
  <LastUpdatedBy>MM-P-C6CFD7A2</LastUpdatedBy>
  <LastUpdateTimeStamp>2017-11-14T09:28:17.533</LastUpdateTimeStamp>
 </Rule>
 <Rule>
  <CountryOrganizationId>DE</CountryOrganizationId>
  <ItemId>C90749AB-614C-069E-941D-22BC04DB8593</ItemId>
  <Context>
   <Process>NO_PROCESS</Process>
   <ProcessStep>DashBoard</ProcessStep>
   <OrganizationId>RS_DE_SV_ALLIANZ_ADMIN</OrganizationId>
  </Context>
  <RuleType>Configuration</RuleType>
  <Key>toolbarTemplate</Key>
  <Value>MaterialDesign/MaterialDesignToolbar.htm</Value>
  <Status>Active</Status>
  <CreatedBy>MM-P-9BBB2219</CreatedBy>
  <CreationTimeStamp>2017-04-13T15:20:07.434</CreationTimeStamp>
  <LastUpdatedBy>MM-P-C6CFD7A2</LastUpdatedBy>
  <LastUpdateTimeStamp>2017-11-14T09:28:17.540</LastUpdateTimeStamp>
 </Rule>
 <Rule>
  <CountryOrganizationId>DE</CountryOrganizationId>
  <ItemId>FAC44DE0-31DC-38F3-9E37-599E64B63DC2</ItemId>
  <Context>
   <OrganizationId>RS_DE_SV_ALLIANZ_ADMIN</OrganizationId>
  </Context>
  <RuleType>DataAccessRight</RuleType>
  <Key>TaskType.CHANGE_OWNER</Key>
  <Value>{"AccessLevel":"","AccessLevelParam":["ML-O-209801"]}</Value>
  <Expression>{"AccessLevel":"SPECIFIC","AccessLevelParam":["ML-O-209801","ML-O-209802"],"DataConstraint":"task.responsibleUserId == '${memberCache.currentMemberId}' || task.responsibleOrganizationId == 'ML-O-209801'"}</Expression>
  <Status>Active</Status>
  <CreatedBy>MM-P-9BBB2219</CreatedBy>
  <CreationTimeStamp>2017-04-13T15:20:07.751</CreationTimeStamp>
  <LastUpdatedBy>MM-P-C6CFD7A2</LastUpdatedBy>
  <LastUpdateTimeStamp>2018-01-12T15:56:39.724</LastUpdateTimeStamp>
 </Rule>
 <Rule>
  <CountryOrganizationId>DE</CountryOrganizationId>
  <ItemId>20DD865F-0958-BB81-0CDA-CD7F2DA4A7CE</ItemId>
  <Context>
   <Process>NO_PROCESS</Process>
   <ProcessStep>flsReassign</ProcessStep>
   <OrganizationId>RS_DE_SV_ALLIANZ_ADMIN</OrganizationId>
  </Context>
  <RuleType>FlowProcessorConfiguration</RuleType>
  <Key>SendTask.SendMessageTaskIf(flsReassign)</Key>
  <Value>{messageSubject: "test reassign", messageBody: "your case '${current.claimNumber}' has beed reassign to '${parameters['RECEIVER'].firstName} ${parameters['RECEIVER'].lastName}'.\nPlease check ${getCaseLinkForWorkPage(current.itemId)}", overWriteEmailNotificationConfig: "true", recipients: "${parameters['ORIGINAL_ASSESSOR_EMAIL']}"}</Value>
  <Status>Active</Status>
  <CreatedBy>MM-P-C6CFD7A2</CreatedBy>
  <CreationTimeStamp>2018-01-11T09:52:45.517</CreationTimeStamp>
  <LastUpdatedBy>MM-P-C6CFD7A2</LastUpdatedBy>
  <LastUpdateTimeStamp>2018-01-11T09:52:45.517</LastUpdateTimeStamp>
 </Rule>
 <Rule>
  <CountryOrganizationId>DE</CountryOrganizationId>
  <ItemId>55DA64F1-4E79-820D-A3AD-C98ADB998A95</ItemId>
  <Context>
   <Process>NO_PROCESS</Process>
   <ProcessStep>flsReassign</ProcessStep>
   <OrganizationId>RS_DE_SV_ALLIANZ_ADMIN</OrganizationId>
  </Context>
  <RuleType>FlowProcessorConfiguration</RuleType>
  <Key>SendTask.POSTACTIONS</Key>
  <Value>[{"name":"FLSNotificationPostAction","alias":"FLSNotificationPostAction(flsReassign)"},{"name":"SendMessageTaskIf","alias":"SendMessageTaskIf(flsReassign)"}]</Value>
  <Status>Active</Status>
  <CreatedBy>MM-P-C6CFD7A2</CreatedBy>
  <CreationTimeStamp>2018-01-11T09:53:11.232</CreationTimeStamp>
  <LastUpdatedBy>MM-P-C6CFD7A2</LastUpdatedBy>
  <LastUpdateTimeStamp>2018-01-11T09:53:11.232</LastUpdateTimeStamp>
 </Rule>
 <Rule>
  <CountryOrganizationId>DE</CountryOrganizationId>
  <ItemId>AD33B3D1-9F29-2CCB-98C7-969929CECA93</ItemId>
  <Context>
   <Process>NO_PROCESS</Process>
   <ProcessStep>MaterialGrid</ProcessStep>
   <OrganizationId>RS_DE_SV_ALLIANZ_ADMIN</OrganizationId>
  </Context>
  <RuleType>Configuration</RuleType>
  <Key>homePath</Key>
  <Value>/bre/work/NO_PROCESS/MaterialGrid?gridView=worklistgrid_open</Value>
  <Status>Active</Status>
  <CreatedBy>MM-P-9BBB2219</CreatedBy>
  <CreationTimeStamp>2017-04-13T15:20:07.124</CreationTimeStamp>
  <LastUpdatedBy>MM-P-C6CFD7A2</LastUpdatedBy>
  <LastUpdateTimeStamp>2017-11-14T09:28:17.309</LastUpdateTimeStamp>
 </Rule>
 <Rule>
  <CountryOrganizationId>DE</CountryOrganizationId>
  <ItemId>5A08F2F3-1602-1520-78B2-5F9D0AB8E3D0</ItemId>
  <Context>
   <OrganizationId>RS_DE_SV_ALLIANZ_ADMIN</OrganizationId>
  </Context>
  <RuleType>DataAccessRight</RuleType>
  <Key>TaskType.DELETE</Key>
  <Value>{"AccessLevel":"","AccessLevelParam":["ML-O-209801"]}</Value>
  <Expression>{"AccessLevel":"SPECIFIC","AccessLevelParam":["ML-O-209801","ML-O-209802"],"DataConstraint":"task.responsibleUserId == '${memberCache.currentMemberId}' || task.responsibleOrganizationId == 'ML-O-209801'"}</Expression>
  <Status>Active</Status>
  <CreatedBy>MM-P-9BBB2219</CreatedBy>
  <CreationTimeStamp>2017-04-13T15:20:07.237</CreationTimeStamp>
  <LastUpdatedBy>MM-P-C6CFD7A2</LastUpdatedBy>
  <LastUpdateTimeStamp>2017-12-18T10:29:54.963</LastUpdateTimeStamp>
 </Rule>
 <Rule>
  <CountryOrganizationId>DE</CountryOrganizationId>
  <ItemId>74C04AF8-713D-D161-96BA-F2E66ACBC43B</ItemId>
  <Context>
   <Process>NO_PROCESS</Process>
   <ProcessStep>DashBoard</ProcessStep>
   <OrganizationId>RS_DE_SV_ALLIANZ_ADMIN</OrganizationId>
  </Context>
  <RuleType>Configuration</RuleType>
  <Key>templatePrefix</Key>
  <Value>MaterialDesign</Value>
  <Status>Active</Status>
  <CreatedBy>MM-P-9BBB2219</CreatedBy>
  <CreationTimeStamp>2017-04-13T15:20:07.688</CreationTimeStamp>
  <LastUpdatedBy>MM-P-C6CFD7A2</LastUpdatedBy>
  <LastUpdateTimeStamp>2017-11-14T09:28:17.375</LastUpdateTimeStamp>
 </Rule>
 <Rule>
  <CountryOrganizationId>DE</CountryOrganizationId>
  <ItemId>8F9F14E0-130F-BB36-6533-BE78CBF1CDAD</ItemId>
  <Context>
   <OrganizationId>RS_DE_SV_ALLIANZ_ADMIN</OrganizationId>
  </Context>
  <RuleType>DataAccessRight</RuleType>
  <Key>TaskType.UNLOCK</Key>
  <Value>{"AccessLevel":"SPECIFIC","AccessLevelParam":["ML-O-209801"]}</Value>
  <Status>Active</Status>
  <CreatedBy>MM-P-9BBB2219</CreatedBy>
  <CreationTimeStamp>2017-04-13T15:20:07.676</CreationTimeStamp>
  <LastUpdatedBy>MM-P-C6CFD7A2</LastUpdatedBy>
  <LastUpdateTimeStamp>2017-12-18T10:29:54.968</LastUpdateTimeStamp>
 </Rule>
 <Rule>
  <CountryOrganizationId>DE</CountryOrganizationId>
  <ItemId>A4C3A4EF-4621-F1D0-76E3-9C2F66DB4AE4</ItemId>
  <Context>
   <Process>NO_PROCESS</Process>
   <ProcessStep>DashBoard</ProcessStep>
   <OrganizationId>RS_DE_SV_ALLIANZ_ADMIN</OrganizationId>
  </Context>
  <RuleType>ProcessTransition</RuleType>
  <Key>DashBoard</Key>
  <Value>DashBoard</Value>
  <Status>Active</Status>
  <CreatedBy>MM-P-9BBB2219</CreatedBy>
  <CreationTimeStamp>2017-04-13T15:20:07.256</CreationTimeStamp>
  <LastUpdatedBy>MM-P-C6CFD7A2</LastUpdatedBy>
  <LastUpdateTimeStamp>2017-11-14T09:28:17.518</LastUpdateTimeStamp>
 </Rule>
 <Rule>
  <CountryOrganizationId>DE</CountryOrganizationId>
  <ItemId>770CF98F-DA61-927E-D29F-C1389BB4F513</ItemId>
  <Context>
   <OrganizationId>RS_DE_SV_ALLIANZ_ADMIN</OrganizationId>
  </Context>
  <RuleType>Configuration</RuleType>
  <Key>bulk_actions_views</Key>
  <Value>worklistgrid_open</Value>
  <Status>Active</Status>
  <CreatedBy>MM-P-C6CFD7A2</CreatedBy>
  <CreationTimeStamp>2017-11-14T09:28:17.523</CreationTimeStamp>
  <LastUpdatedBy>MM-P-C6CFD7A2</LastUpdatedBy>
  <LastUpdateTimeStamp>2017-11-14T09:28:17.523</LastUpdateTimeStamp>
 </Rule>
 <Rule>
  <CountryOrganizationId>DE</CountryOrganizationId>
  <ItemId>5A860970-A343-0818-E393-3E8546D0ECE7</ItemId>
  <Context>
   <OrganizationId>RS_DE_SV_ALLIANZ_ADMIN</OrganizationId>
  </Context>
  <RuleType>DataAccessRight</RuleType>
  <Key>TaskType.READ</Key>
  <Value>{"AccessLevel":"","AccessLevelParam":["ML-O-209801","ML-O-209802"]}</Value>
  <Expression>{"AccessLevel":"SPECIFIC","AccessLevelParam":["ML-O-209801","ML-O-209802"],"DataConstraint":"task.responsibleUserId == '${memberCache.currentMemberId}' || task.responsibleOrganizationId == 'ML-O-209801'"}</Expression>
  <Status>Active</Status>
  <CreatedBy>MM-P-9BBB2219</CreatedBy>
  <CreationTimeStamp>2017-04-13T15:20:07.521</CreationTimeStamp>
  <LastUpdatedBy>MM-P-C6CFD7A2</LastUpdatedBy>
  <LastUpdateTimeStamp>2017-12-18T10:29:54.972</LastUpdateTimeStamp>
 </Rule>
 <Rule>
  <CountryOrganizationId>DE</CountryOrganizationId>
  <ItemId>19FA0B62-1B11-B29E-1AB8-BF6094F10263</ItemId>
  <Context>
   <Process>NO_PROCESS</Process>
   <ProcessStep>flsReassign</ProcessStep>
   <OrganizationId>RS_DE_SV_ALLIANZ_ADMIN</OrganizationId>
  </Context>
  <RuleType>FlowProcessorConfiguration</RuleType>
  <Key>ChangeTaskOwnerWorkflowFunction.SendMessageTaskIf(1513588971418)</Key>
  <Value>{messageSubject: "Case reassign", messageBody: "Your case '${current.claimNumber}' has beed reassigned to '${current.responsibleUserFirstName} ${current.responsibleUserLastName}'.\nPlease check ${getCaseLinkForWorkPage(current.itemId)}", overWriteEmailNotificationConfig: "true", recipients: "${parameters['ORIGINAL_ASSESSOR_EMAIL']}"}</Value>
  <Status>Active</Status>
  <CreatedBy>MM-P-C6CFD7A2</CreatedBy>
  <CreationTimeStamp>2017-12-18T10:23:54.135</CreationTimeStamp>
  <LastUpdatedBy>MM-P-C6CFD7A2</LastUpdatedBy>
  <LastUpdateTimeStamp>2017-12-18T10:23:54.135</LastUpdateTimeStamp>
 </Rule>
 <Rule>
  <CountryOrganizationId>DE</CountryOrganizationId>
  <ItemId>0ED91680-4B8C-CFB5-61D1-4F31B12FEC1A</ItemId>
  <Context>
   <OrganizationId>RS_DE_SV_ALLIANZ_ADMIN</OrganizationId>
  </Context>
  <RuleType>DataAccessRight</RuleType>
  <Key>TaskType.RECALL</Key>
  <Value>{"AccessLevel":"SELF","AccessLevelParam":[]}</Value>
  <Status>Active</Status>
  <CreatedBy>MM-P-9BBB2219</CreatedBy>
  <CreationTimeStamp>2017-04-13T15:20:07.600</CreationTimeStamp>
  <LastUpdatedBy>MM-P-C6CFD7A2</LastUpdatedBy>
  <LastUpdateTimeStamp>2017-12-18T10:29:54.980</LastUpdateTimeStamp>
 </Rule>
 <Rule>
  <CountryOrganizationId>DE</CountryOrganizationId>
  <ItemId>09DA37B8-B187-F390-E08F-F6F982BD2CA7</ItemId>
  <Context>
   <Process>NO_PROCESS</Process>
   <ProcessStep>WorkListGrid</ProcessStep>
   <OrganizationId>RS_DE_SV_ALLIANZ_ADMIN</OrganizationId>
  </Context>
  <RuleType>Configuration</RuleType>
  <Key>views</Key>
  <Value>worklistgrid_copied,worklistgrid_open,worklistgrid_sent,worklistgrid_closed,worklistgrid_deleted</Value>
  <Status>Active</Status>
  <CreatedBy>MM-P-9BBB2219</CreatedBy>
  <CreationTimeStamp>2017-04-13T15:20:07.771</CreationTimeStamp>
  <LastUpdatedBy>MM-P-C6CFD7A2</LastUpdatedBy>
  <LastUpdateTimeStamp>2018-01-22T09:27:12.186</LastUpdateTimeStamp>
 </Rule>
 <Rule>
  <CountryOrganizationId>DE</CountryOrganizationId>
  <ItemId>20ED1C4C-04B1-D46A-387F-80E4C43A0BC9</ItemId>
  <Context>
   <OrganizationId>RS_DE_SV_ALLIANZ_ADMIN</OrganizationId>
  </Context>
  <RuleType>Configuration</RuleType>
  <Key>homePath</Key>
  <Value>/bre/work/NO_PROCESS/MaterialGrid?gridView=worklistgrid_open</Value>
  <Status>Active</Status>
  <CreatedBy>MM-P-C6CFD7A2</CreatedBy>
  <CreationTimeStamp>2017-11-14T09:28:17.315</CreationTimeStamp>
  <LastUpdatedBy>MM-P-C6CFD7A2</LastUpdatedBy>
  <LastUpdateTimeStamp>2017-11-14T09:28:17.315</LastUpdateTimeStamp>
 </Rule>
 <Rule>
  <CountryOrganizationId>DE</CountryOrganizationId>
  <ItemId>5586E73F-8C40-FBCA-1449-2FCE832CA995</ItemId>
  <Context>
   <OrganizationId>RS_DE_SV_ALLIANZ_ADMIN</OrganizationId>
  </Context>
  <RuleType>DataAccessRight</RuleType>
  <Key>TaskType.MOVE</Key>
  <Value>{"AccessLevel":"SPECIFIC","AccessLevelParam":["ML-O-209801"]}</Value>
  <Status>Active</Status>
  <CreatedBy>MM-P-9BBB2219</CreatedBy>
  <CreationTimeStamp>2017-04-13T15:20:07.377</CreationTimeStamp>
  <LastUpdatedBy>MM-P-C6CFD7A2</LastUpdatedBy>
  <LastUpdateTimeStamp>2017-12-18T10:29:54.984</LastUpdateTimeStamp>
 </Rule>
 <Rule>
  <CountryOrganizationId>DE</CountryOrganizationId>
  <ItemId>6860D9A2-939F-186A-1E03-068E18D443E7</ItemId>
  <Context>
   <Process>NO_PROCESS</Process>
   <ProcessStep>DashBoard</ProcessStep>
   <OrganizationId>RS_DE_SV_ALLIANZ_ADMIN</OrganizationId>
  </Context>
  <RuleType>FieldVisibility</RuleType>
  <Key>root.dashboard</Key>
  <Value>show</Value>
  <Status>Active</Status>
  <CreatedBy>MM-P-9BBB2219</CreatedBy>
  <CreationTimeStamp>2017-04-13T15:20:07.332</CreationTimeStamp>
  <LastUpdatedBy>MM-P-C6CFD7A2</LastUpdatedBy>
  <LastUpdateTimeStamp>2017-11-14T09:28:17.363</LastUpdateTimeStamp>
 </Rule>
 <Rule>
  <CountryOrganizationId>DE</CountryOrganizationId>
  <ItemId>85317925-22EB-7F75-ADD0-4C8645A69A92</ItemId>
  <Context>
   <OrganizationId>RS_DE_SV_ALLIANZ_ADMIN</OrganizationId>
  </Context>
  <RuleType>DataAccessRight</RuleType>
  <Key>TaskType.CREATE</Key>
  <Value>{"AccessLevel":"SELF","AccessLevelParam":[]}</Value>
  <Status>Active</Status>
  <CreatedBy>MM-P-9BBB2219</CreatedBy>
  <CreationTimeStamp>2017-04-13T15:20:07.577</CreationTimeStamp>
  <LastUpdatedBy>MM-P-C6CFD7A2</LastUpdatedBy>
  <LastUpdateTimeStamp>2017-12-18T10:29:54.989</LastUpdateTimeStamp>
 </Rule>
 <Rule>
  <CountryOrganizationId>DE</CountryOrganizationId>
  <ItemId>29D2FED6-75BC-BBC1-990E-498C0DDAC4E6</ItemId>
  <Context>
   <Process>NO_PROCESS</Process>
   <ProcessStep>DashBoard</ProcessStep>
   <OrganizationId>RS_DE_SV_ALLIANZ_ADMIN</OrganizationId>
  </Context>
  <RuleType>Configuration</RuleType>
  <Key>pageTemplate</Key>
  <Value>MaterialDesign/MaterialDesignPage.htm</Value>
  <Status>Active</Status>
  <CreatedBy>MM-P-9BBB2219</CreatedBy>
  <CreationTimeStamp>2017-04-13T15:20:07.530</CreationTimeStamp>
  <LastUpdatedBy>MM-P-C6CFD7A2</LastUpdatedBy>
  <LastUpdateTimeStamp>2017-11-14T09:28:17.435</LastUpdateTimeStamp>
 </Rule>
 <Rule>
  <CountryOrganizationId>DE</CountryOrganizationId>
  <ItemId>444317E7-C39B-FCED-2D46-6D3F8851A855</ItemId>
  <Context>
   <Process>MasterData</Process>
   <OrganizationId>RS_DE_SV_ALLIANZ_ADMIN</OrganizationId>
  </Context>
  <RuleType>Configuration</RuleType>
  <Key>pageTemplate</Key>
  <Value>MaterialDesign/MaterialDesignPage.htm</Value>
  <Status>Active</Status>
  <CreatedBy>MM-P-9BBB2219</CreatedBy>
  <CreationTimeStamp>2017-04-13T15:20:07.437</CreationTimeStamp>
  <LastUpdatedBy>MM-P-C6CFD7A2</LastUpdatedBy>
  <LastUpdateTimeStamp>2017-11-14T09:28:17.454</LastUpdateTimeStamp>
 </Rule>
 <Rule>
  <CountryOrganizationId>DE</CountryOrganizationId>
  <ItemId>4C91EB8C-9021-0688-B2BE-CB2833F4C155</ItemId>
  <Context>
   <Process>NO_PROCESS</Process>
   <ProcessStep>DashBoard</ProcessStep>
   <OrganizationId>RS_DE_SV_ALLIANZ_ADMIN</OrganizationId>
  </Context>
  <RuleType>Block</RuleType>
  <Key>blockNames</Key>
  <Value>dashboard</Value>
  <Status>Active</Status>
  <CreatedBy>MM-P-9BBB2219</CreatedBy>
  <CreationTimeStamp>2017-04-13T15:20:07.422</CreationTimeStamp>
  <LastUpdatedBy>MM-P-C6CFD7A2</LastUpdatedBy>
  <LastUpdateTimeStamp>2017-11-14T09:28:17.467</LastUpdateTimeStamp>
 </Rule>
 <Rule>
  <CountryOrganizationId>DE</CountryOrganizationId>
  <ItemId>D0502F8C-6EAC-78F5-25C5-D072C60B345F</ItemId>
  <Context>
   <OrganizationId>RS_DE_SV_ALLIANZ_ADMIN</OrganizationId>
  </Context>
  <RuleType>Configuration</RuleType>
  <Key>staticPages</Key>
  <Value>DashBoard</Value>
  <Status>Active</Status>
  <CreatedBy>MM-P-9BBB2219</CreatedBy>
  <CreationTimeStamp>2017-04-13T15:20:07.164</CreationTimeStamp>
  <LastUpdatedBy>MM-P-C6CFD7A2</LastUpdatedBy>
  <LastUpdateTimeStamp>2017-11-14T09:28:17.551</LastUpdateTimeStamp>
 </Rule>
 <Rule>
  <CountryOrganizationId>DE</CountryOrganizationId>
  <ItemId>87267724-C094-484B-050B-E5E0BCF03B6C</ItemId>
  <Context>
   <Process>MasterData</Process>
   <OrganizationId>RS_DE_SV_ALLIANZ_ADMIN</OrganizationId>
  </Context>
  <RuleType>Configuration</RuleType>
  <Key>MemberContactListAddressRole</Key>
  <Value>Business</Value>
  <Status>Active</Status>
  <CreatedBy>MM-P-C6CFD7A2</CreatedBy>
  <CreationTimeStamp>2017-04-20T10:49:43.600</CreationTimeStamp>
  <LastUpdatedBy>MM-P-C6CFD7A2</LastUpdatedBy>
  <LastUpdateTimeStamp>2017-11-14T09:28:17.408</LastUpdateTimeStamp>
 </Rule>
 <Rule>
  <CountryOrganizationId>DE</CountryOrganizationId>
  <ItemId>8A9F0897-6EC7-E0F8-C0BD-CBE8D12A393F</ItemId>
  <Context>
   <Process>NO_PROCESS</Process>
   <ProcessStep>DashBoard</ProcessStep>
   <OrganizationId>RS_DE_SV_ALLIANZ_ADMIN</OrganizationId>
  </Context>
  <RuleType>Configuration</RuleType>
  <Key>dashboard.widget1.icon</Key>
  <Value>list</Value>
  <Status>Active</Status>
  <CreatedBy>MM-P-9BBB2219</CreatedBy>
  <CreationTimeStamp>2017-04-13T15:20:07.287</CreationTimeStamp>
  <LastUpdatedBy>MM-P-C6CFD7A2</LastUpdatedBy>
  <LastUpdateTimeStamp>2017-11-14T09:28:17.412</LastUpdateTimeStamp>
 </Rule>
 <Rule>
  <CountryOrganizationId>DE</CountryOrganizationId>
  <ItemId>54102992-D752-E7F1-3A31-488FDF499FE4</ItemId>
  <Context>
   <OrganizationId>RS_DE_SV_ALLIANZ_ADMIN</OrganizationId>
  </Context>
  <RuleType>DataAccessRight</RuleType>
  <Key>TaskType.CLOSE</Key>
  <Value>{"AccessLevel":"","AccessLevelParam":["ML-O-209801"]}</Value>
  <Expression>{"AccessLevel":"SPECIFIC","AccessLevelParam":["ML-O-209801","ML-O-209802"],"DataConstraint":"task.responsibleUserId == '${memberCache.currentMemberId}' || task.responsibleOrganizationId == 'ML-O-209801'"}</Expression>
  <Status>Active</Status>
  <CreatedBy>MM-P-9BBB2219</CreatedBy>
  <CreationTimeStamp>2017-04-13T15:20:07.697</CreationTimeStamp>
  <LastUpdatedBy>MM-P-C6CFD7A2</LastUpdatedBy>
  <LastUpdateTimeStamp>2017-12-18T10:29:54.993</LastUpdateTimeStamp>
 </Rule>
 <Rule>
  <CountryOrganizationId>DE</CountryOrganizationId>
  <ItemId>0022049F-3BE8-1315-0E38-5BB27B448E00</ItemId>
  <Context>
   <Process>NO_PROCESS</Process>
   <ProcessStep>WorkListGrid</ProcessStep>
   <OrganizationId>RS_DE_SV_ALLIANZ_ADMIN</OrganizationId>
  </Context>
  <RuleType>Configuration</RuleType>
  <Key>WorkListGrid.action.worklistgrid_sent</Key>
  <Value>PrintPdf</Value>
  <Status>Active</Status>
  <CreatedBy>MM-P-9BBB2219</CreatedBy>
  <CreationTimeStamp>2017-04-13T15:20:07.756</CreationTimeStamp>
  <LastUpdatedBy>MM-P-C6CFD7A2</LastUpdatedBy>
  <LastUpdateTimeStamp>2017-11-22T20:18:45.001</LastUpdateTimeStamp>
 </Rule>
 <Rule>
  <CountryOrganizationId>DE</CountryOrganizationId>
  <ItemId>D2C44B70-7EF7-E6A9-4168-13ACB46A7A20</ItemId>
  <Context>
   <Process>MasterData</Process>
   <OrganizationId>RS_DE_SV_ALLIANZ_ADMIN</OrganizationId>
  </Context>
  <RuleType>Configuration</RuleType>
  <Key>headerTemplate</Key>
  <Value>MaterialDesign/MaterialDesignHeader.htm</Value>
  <Status>Active</Status>
  <CreatedBy>MM-P-9BBB2219</CreatedBy>
  <CreationTimeStamp>2017-04-13T15:20:07.707</CreationTimeStamp>
  <LastUpdatedBy>MM-P-C6CFD7A2</LastUpdatedBy>
  <LastUpdateTimeStamp>2017-11-14T09:28:17.557</LastUpdateTimeStamp>
 </Rule>
 <Rule>
  <CountryOrganizationId>DE</CountryOrganizationId>
  <ItemId>6CD92BFD-82BD-077D-4974-C5EC781BFEA3</ItemId>
  <Context>
   <Process>NO_PROCESS</Process>
   <ProcessStep>WorkListGrid</ProcessStep>
   <OrganizationId>RS_DE_SV_ALLIANZ_ADMIN</OrganizationId>
  </Context>
  <RuleType>Configuration</RuleType>
  <Key>homePath</Key>
  <Value>/bre/work/NO_PROCESS/MaterialGrid?gridView=worklistgrid_open</Value>
  <Status>Active</Status>
  <CreatedBy>MM-P-C6CFD7A2</CreatedBy>
  <CreationTimeStamp>2017-11-14T09:28:17.589</CreationTimeStamp>
  <LastUpdatedBy>MM-P-C6CFD7A2</LastUpdatedBy>
  <LastUpdateTimeStamp>2017-11-14T09:28:17.589</LastUpdateTimeStamp>
 </Rule>
 <Rule>
  <CountryOrganizationId>DE</CountryOrganizationId>
  <ItemId>6E7EC367-A35F-779C-57B9-87962173382F</ItemId>
  <Context>
   <Process>NO_PROCESS</Process>
   <ProcessStep>DashBoard</ProcessStep>
   <OrganizationId>RS_DE_SV_ALLIANZ_ADMIN</OrganizationId>
  </Context>
  <RuleType>Configuration</RuleType>
  <Key>dashboard.widget2.label</Key>
  <Value>desn.header.settings</Value>
  <Status>Active</Status>
  <CreatedBy>MM-P-9BBB2219</CreatedBy>
  <CreationTimeStamp>2017-04-13T15:20:07.625</CreationTimeStamp>
  <LastUpdatedBy>MM-P-C6CFD7A2</LastUpdatedBy>
  <LastUpdateTimeStamp>2017-11-14T09:28:17.369</LastUpdateTimeStamp>
 </Rule>
 <Rule>
  <CountryOrganizationId>DE</CountryOrganizationId>
  <ItemId>E8E942F4-B0F6-F274-99B4-99D4E19C7B20</ItemId>
  <Context>
   <Process>NO_PROCESS</Process>
   <ProcessStep>flsReassign</ProcessStep>
   <OrganizationId>RS_DE_SV_ALLIANZ_ADMIN</OrganizationId>
  </Context>
  <RuleType>FlowProcessorConfiguration</RuleType>
  <Key>ChangeTaskOwnerWorkflowFunction.TRANSFORMATIONS</Key>
  <Value>[{"name":"KADFlsPrintTransformation","alias":"KADFlsPrintTransformation(1511788174906)"},{"name":"FLSAssessorAssignmentNotificationTransformation","alias":"FLSAssessorAssignmentNotificationTransformation(flsReassign2)"}]</Value>
  <Status>Active</Status>
  <CreatedBy>MM-P-C6CFD7A2</CreatedBy>
  <CreationTimeStamp>2017-12-18T10:22:00.784</CreationTimeStamp>
  <LastUpdatedBy>MM-P-C6CFD7A2</LastUpdatedBy>
  <LastUpdateTimeStamp>2018-01-11T10:02:05.435</LastUpdateTimeStamp>
 </Rule>
 <Rule>
  <CountryOrganizationId>DE</CountryOrganizationId>
  <ItemId>55D04CF0-29DE-8760-A440-F8EF88EE0EEC</ItemId>
  <Context>
   <Process>NO_PROCESS</Process>
   <ProcessStep>DashBoard</ProcessStep>
   <OrganizationId>RS_DE_SV_ALLIANZ_ADMIN</OrganizationId>
  </Context>
  <RuleType>Configuration</RuleType>
  <Key>dashboard.widget1.url</Key>
  <Value>/bre/work/NO_PROCESS/MaterialGrid?gridView=worklistgrid_open</Value>
  <Status>Active</Status>
  <CreatedBy>MM-P-9BBB2219</CreatedBy>
  <CreationTimeStamp>2017-04-13T15:20:07.549</CreationTimeStamp>
  <LastUpdatedBy>MM-P-C6CFD7A2</LastUpdatedBy>
  <LastUpdateTimeStamp>2017-11-14T09:28:17.348</LastUpdateTimeStamp>
 </Rule>
 <Rule>
  <CountryOrganizationId>DE</CountryOrganizationId>
  <ItemId>8DC5B30C-F007-58C4-9223-F9035D381F03</ItemId>
  <Context>
   <Process>NO_PROCESS</Process>
   <ProcessStep>DashBoard</ProcessStep>
   <OrganizationId>RS_DE_SV_ALLIANZ_ADMIN</OrganizationId>
  </Context>
  <RuleType>Configuration</RuleType>
  <Key>dashboard.widget1.label</Key>
  <Value>repairwatch.dashboard.widget.worklistgrid</Value>
  <Status>Active</Status>
  <CreatedBy>MM-P-9BBB2219</CreatedBy>
  <CreationTimeStamp>2017-04-13T15:20:07.618</CreationTimeStamp>
  <LastUpdatedBy>MM-P-C6CFD7A2</LastUpdatedBy>
  <LastUpdateTimeStamp>2017-11-14T09:28:17.416</LastUpdateTimeStamp>
 </Rule>
 <Rule>
  <CountryOrganizationId>DE</CountryOrganizationId>
  <ItemId>1FEC05CE-BF09-3B61-D471-4337C3AD4D87</ItemId>
  <Context>
   <Process>NO_PROCESS</Process>
   <ProcessStep>DashBoard</ProcessStep>
   <OrganizationId>RS_DE_SV_ALLIANZ_ADMIN</OrganizationId>
  </Context>
  <RuleType>Block</RuleType>
  <Key>dashboard</Key>
  <Value>root.dashboard</Value>
  <Status>Active</Status>
  <CreatedBy>MM-P-9BBB2219</CreatedBy>
  <CreationTimeStamp>2017-04-13T15:20:07.281</CreationTimeStamp>
  <LastUpdatedBy>MM-P-C6CFD7A2</LastUpdatedBy>
  <LastUpdateTimeStamp>2017-11-14T09:28:17.430</LastUpdateTimeStamp>
 </Rule>
 <Rule>
  <CountryOrganizationId>DE</CountryOrganizationId>
  <ItemId>46965474-D4B6-90D5-9052-A9D06434617D</ItemId>
  <Context>
   <Process>MasterData</Process>
   <OrganizationId>RS_DE_SV_ALLIANZ_ADMIN</OrganizationId>
  </Context>
  <RuleType>Configuration</RuleType>
  <Key>homePath</Key>
  <Value>/bre/work/NO_PROCESS/DashBoard</Value>
  <Status>Active</Status>
  <CreatedBy>MM-P-9BBB2219</CreatedBy>
  <CreationTimeStamp>2017-04-13T15:20:07.190</CreationTimeStamp>
  <LastUpdatedBy>MM-P-C6CFD7A2</LastUpdatedBy>
  <LastUpdateTimeStamp>2017-11-14T09:28:17.460</LastUpdateTimeStamp>
 </Rule>
 <Rule>
  <CountryOrganizationId>DE</CountryOrganizationId>
  <ItemId>CE0B6FA3-7A53-BB0D-ACCA-BFF7DD528EF3</ItemId>
  <Context>
   <Process>MasterData</Process>
   <OrganizationId>RS_DE_SV_ALLIANZ_ADMIN</OrganizationId>
  </Context>
  <RuleType>Configuration</RuleType>
  <Key>menuTemplate</Key>
  <Value>MaterialDesign/MaterialDesignMenu.htm</Value>
  <Status>Active</Status>
  <CreatedBy>MM-P-9BBB2219</CreatedBy>
  <CreationTimeStamp>2017-04-13T15:20:07.205</CreationTimeStamp>
  <LastUpdatedBy>MM-P-C6CFD7A2</LastUpdatedBy>
  <LastUpdateTimeStamp>2017-11-14T09:28:17.545</LastUpdateTimeStamp>
 </Rule>
 <Rule>
  <CountryOrganizationId>DE</CountryOrganizationId>
  <ItemId>E2518B00-6FD6-4F19-77B6-56C6CB8D3645</ItemId>
  <Context>
   <Process>NO_PROCESS</Process>
   <ProcessStep>WorkListGrid</ProcessStep>
   <OrganizationId>RS_DE_SV_ALLIANZ_ADMIN</OrganizationId>
  </Context>
  <RuleType>Configuration</RuleType>
  <Key>WorkListGrid.action.worklistgrid_open</Key>
  <Value>DeleteTask,PrintPdf,CopyIntoNewCase,CloseCase,ChangeTaskOwner,assignToMe</Value>
  <Status>Active</Status>
  <CreatedBy>MM-P-9BBB2219</CreatedBy>
  <CreationTimeStamp>2017-04-13T15:20:07.787</CreationTimeStamp>
  <LastUpdatedBy>MM-P-C6CFD7A2</LastUpdatedBy>
  <LastUpdateTimeStamp>2017-11-22T09:24:07.931</LastUpdateTimeStamp>
 </Rule>
 <Rule>
  <CountryOrganizationId>DE</CountryOrganizationId>
  <ItemId>0B619BA2-C17B-3AED-4AB9-C4D48DA9B3C8</ItemId>
  <Context>
   <OrganizationId>RS_DE_SV_ALLIANZ_ADMIN</OrganizationId>
  </Context>
  <RuleType>DataAccessRight</RuleType>
  <Key>TaskType.UPDATE</Key>
  <Value>{"AccessLevel":"SELF","AccessLevelParam":[]}</Value>
  <Status>Active</Status>
  <CreatedBy>MM-P-9BBB2219</CreatedBy>
  <CreationTimeStamp>2017-04-13T15:20:07.353</CreationTimeStamp>
  <LastUpdatedBy>MM-P-C6CFD7A2</LastUpdatedBy>
  <LastUpdateTimeStamp>2017-12-18T10:29:54.998</LastUpdateTimeStamp>
 </Rule>
 <Rule>
  <CountryOrganizationId>DE</CountryOrganizationId>
  <ItemId>63AEB1F5-DFE4-7FFF-BFDC-5BFF5F8FEDD6</ItemId>
  <Context>
   <Process>NO_PROCESS</Process>
   <ProcessStep>flsReassign</ProcessStep>
   <OrganizationId>RS_DE_SV_ALLIANZ_ADMIN</OrganizationId>
  </Context>
  <RuleType>FlowProcessorConfiguration</RuleType>
  <Key>ChangeTaskOwnerWorkflowFunction.POSTACTIONS</Key>
  <Value>[{"name":"FLSNotificationPostAction","alias":"FLSNotificationPostAction(1513588963780)"},{"name":"SendMessageTaskIf","alias":"SendMessageTaskIf(1513588971418)"}]</Value>
  <Status>Active</Status>
  <CreatedBy>MM-P-C6CFD7A2</CreatedBy>
  <CreationTimeStamp>2017-12-18T10:22:43.923</CreationTimeStamp>
  <LastUpdatedBy>MM-P-C6CFD7A2</LastUpdatedBy>
  <LastUpdateTimeStamp>2017-12-18T10:22:51.547</LastUpdateTimeStamp>
 </Rule>
 <Rule>
  <CountryOrganizationId>DE</CountryOrganizationId>
  <ItemId>763A5495-2B26-A0E8-7084-46070C87F03B</ItemId>
  <Context>
   <Process>NO_PROCESS</Process>
   <ProcessStep>DashBoard</ProcessStep>
   <OrganizationId>RS_DE_SV_ALLIANZ_ADMIN</OrganizationId>
  </Context>
  <RuleType>BlockTranslation</RuleType>
  <Key>dashboard</Key>
  <Value>DE=</Value>
  <Status>Active</Status>
  <CreatedBy>MM-P-9BBB2219</CreatedBy>
  <CreationTimeStamp>2017-04-13T15:20:07.728</CreationTimeStamp>
  <LastUpdatedBy>MM-P-C6CFD7A2</LastUpdatedBy>
  <LastUpdateTimeStamp>2017-11-14T09:28:17.382</LastUpdateTimeStamp>
 </Rule>
 <Rule>
  <CountryOrganizationId>DE</CountryOrganizationId>
  <ItemId>7E404859-1AB0-A2A9-5E63-F0034F8E0880</ItemId>
  <Context>
   <Process>NO_PROCESS</Process>
   <ProcessStep>WorkListGrid</ProcessStep>
   <OrganizationId>RS_DE_SV_ALLIANZ_ADMIN</OrganizationId>
  </Context>
  <RuleType>Configuration</RuleType>
  <Key>WorkListGrid.action.worklistgrid_deleted</Key>
  <Value>ReopenTask,CopyIntoNewCase</Value>
  <Status>Active</Status>
  <CreatedBy>MM-P-9BBB2219</CreatedBy>
  <CreationTimeStamp>2017-04-13T15:20:07.397</CreationTimeStamp>
  <LastUpdatedBy>MM-P-C6CFD7A2</LastUpdatedBy>
  <LastUpdateTimeStamp>2017-11-22T20:18:16.079</LastUpdateTimeStamp>
 </Rule>
 <Rule>
  <CountryOrganizationId>DE</CountryOrganizationId>
  <ItemId>3F532054-2C2B-6659-D8BF-B3FAAE5E59DC</ItemId>
  <Context>
   <Process>NO_PROCESS</Process>
   <ProcessStep>DashBoard</ProcessStep>
   <OrganizationId>RS_DE_SV_ALLIANZ_ADMIN</OrganizationId>
  </Context>
  <RuleType>Configuration</RuleType>
  <Key>dashboard.widget2.icon</Key>
  <Value>settings</Value>
  <Status>Active</Status>
  <CreatedBy>MM-P-9BBB2219</CreatedBy>
  <CreationTimeStamp>2017-04-13T15:20:07.565</CreationTimeStamp>
  <LastUpdatedBy>MM-P-C6CFD7A2</LastUpdatedBy>
  <LastUpdateTimeStamp>2017-11-14T09:28:17.445</LastUpdateTimeStamp>
 </Rule>
 <Rule>
  <CountryOrganizationId>DE</CountryOrganizationId>
  <ItemId>A491B3FE-9CDF-D122-24EC-3A4E3A1F7F4C</ItemId>
  <Context>
   <Process>MasterData</Process>
   <OrganizationId>RS_DE_SV_ALLIANZ_ADMIN</OrganizationId>
  </Context>
  <RuleType>Configuration</RuleType>
  <Key>memberContactListColumns</Key>
  <Value>companyName,role,street,city,zipCode</Value>
  <Status>Active</Status>
  <CreatedBy>MM-P-C6CFD7A2</CreatedBy>
  <CreationTimeStamp>2017-04-20T10:26:34.006</CreationTimeStamp>
  <LastUpdatedBy>MM-P-C6CFD7A2</LastUpdatedBy>
  <LastUpdateTimeStamp>2017-11-14T09:28:17.512</LastUpdateTimeStamp>
 </Rule>
 <Rule>
  <CountryOrganizationId>DE</CountryOrganizationId>
  <ItemId>EE7EA5CD-C707-E00B-AB08-6972DD8F32D3</ItemId>
  <Context>
   <Process>MasterData</Process>
   <OrganizationId>RS_DE_SV_ALLIANZ_ADMIN</OrganizationId>
  </Context>
  <RuleType>Configuration</RuleType>
  <Key>pageDialogTemplate</Key>
  <Value>MaterialDesign/MaterialDesignSlideoutPage.htm</Value>
  <Status>Active</Status>
  <CreatedBy>MM-P-9BBB2219</CreatedBy>
  <CreationTimeStamp>2017-04-13T15:20:07.454</CreationTimeStamp>
  <LastUpdatedBy>MM-P-C6CFD7A2</LastUpdatedBy>
  <LastUpdateTimeStamp>2017-11-14T09:28:17.573</LastUpdateTimeStamp>
 </Rule>
 <Rule>
  <CountryOrganizationId>DE</CountryOrganizationId>
  <ItemId>DD2D413F-97A0-0EA9-8593-A3FC71B9DC0E</ItemId>
  <Context>
   <OrganizationId>RS_DE_SV_ALLIANZ_ADMIN</OrganizationId>
  </Context>
  <RuleType>DataAccessRight</RuleType>
  <Key>TaskType.MERGE</Key>
  <Value>{"AccessLevel":"SELF","AccessLevelParam":[]}</Value>
  <Status>Active</Status>
  <CreatedBy>MM-P-9BBB2219</CreatedBy>
  <CreationTimeStamp>2017-04-13T15:20:07.584</CreationTimeStamp>
  <LastUpdatedBy>MM-P-C6CFD7A2</LastUpdatedBy>
  <LastUpdateTimeStamp>2017-12-18T10:29:55.002</LastUpdateTimeStamp>
 </Rule>
 <Rule>
  <CountryOrganizationId>DE</CountryOrganizationId>
  <ItemId>7FB55CE7-8863-4B15-7257-1C1657E943EA</ItemId>
  <Context>
   <OrganizationId>RS_DE_SV_ALLIANZ_ADMIN</OrganizationId>
  </Context>
  <RuleType>Configuration</RuleType>
  <Key>overridenHomeURL</Key>
  <Value>/bre/work/NO_PROCESS/DashBoard?pageViewpoint=MAIN</Value>
  <Status>Active</Status>
  <CreatedBy>MM-P-9BBB2219</CreatedBy>
  <CreationTimeStamp>2017-04-13T15:20:07.311</CreationTimeStamp>
  <LastUpdatedBy>MM-P-C6CFD7A2</LastUpdatedBy>
  <LastUpdateTimeStamp>2018-01-22T09:29:22.959</LastUpdateTimeStamp>
 </Rule>
 <Rule>
  <CountryOrganizationId>DE</CountryOrganizationId>
  <ItemId>144F9A79-9ED1-ACB1-C99E-EABC532FF4BB</ItemId>
  <Context>
   <Process>MasterData</Process>
   <OrganizationId>RS_DE_SV_ALLIANZ_ADMIN</OrganizationId>
  </Context>
  <RuleType>Configuration</RuleType>
  <Key>fixedSteps</Key>
  <Value>MemberContactList,CsaDocumentTemplateList,CsaDocumentTextBlockList,CsaDocumentImport</Value>
  <Status>Active</Status>
  <CreatedBy>MM-P-9BBB2219</CreatedBy>
  <CreationTimeStamp>2017-04-13T15:20:07.717</CreationTimeStamp>
  <LastUpdatedBy>MM-P-C6CFD7A2</LastUpdatedBy>
  <LastUpdateTimeStamp>2017-11-14T09:28:17.505</LastUpdateTimeStamp>
 </Rule>
 <Rule>
  <CountryOrganizationId>DE</CountryOrganizationId>
  <ItemId>0A938357-255A-1368-C604-D90F0E50491B</ItemId>
  <Context>
   <Process>NO_PROCESS</Process>
   <ProcessStep>WorkListGrid</ProcessStep>
   <OrganizationId>RS_DE_SV_ALLIANZ_ADMIN</OrganizationId>
  </Context>
  <RuleType>Configuration</RuleType>
  <Key>WorkListGrid.action.worklistgrid_copied</Key>
  <Value>MergeTask</Value>
  <Status>Active</Status>
  <CreatedBy>MM-P-9BBB2219</CreatedBy>
  <CreationTimeStamp>2017-04-13T15:20:07.765</CreationTimeStamp>
  <LastUpdatedBy>MM-P-C6CFD7A2</LastUpdatedBy>
  <LastUpdateTimeStamp>2017-11-22T20:18:34.419</LastUpdateTimeStamp>
 </Rule>
 <Rule>
  <CountryOrganizationId>DE</CountryOrganizationId>
  <ItemId>0C7A0F14-0696-3377-8800-17BAE8FC26EC</ItemId>
  <Context>
   <Process>NO_PROCESS</Process>
   <ProcessStep>DashBoard</ProcessStep>
   <OrganizationId>RS_DE_SV_ALLIANZ_ADMIN</OrganizationId>
  </Context>
  <RuleType>Configuration</RuleType>
  <Key>dashboard.widget2.url</Key>
  <Value>/bre/work/MasterData/MemberContactList</Value>
  <Status>Active</Status>
  <CreatedBy>MM-P-9BBB2219</CreatedBy>
  <CreationTimeStamp>2017-04-13T15:20:07.305</CreationTimeStamp>
  <LastUpdatedBy>MM-P-C6CFD7A2</LastUpdatedBy>
  <LastUpdateTimeStamp>2017-11-14T09:28:17.330</LastUpdateTimeStamp>
 </Rule>
 <Rule>
  <CountryOrganizationId>DE</CountryOrganizationId>
  <ItemId>A11345DE-CAF4-260C-1497-526F261CA609</ItemId>
  <Context>
   <OrganizationId>RS_DE_SV_ALLIANZ_ADMIN</OrganizationId>
  </Context>
  <RuleType>DataAccessRight</RuleType>
  <Key>TaskType.EDIT</Key>
  <Value>{"AccessLevel":"SELF","AccessLevelParam":[]}</Value>
  <Status>Active</Status>
  <CreatedBy>MM-P-9BBB2219</CreatedBy>
  <CreationTimeStamp>2017-04-13T15:20:07.357</CreationTimeStamp>
  <LastUpdatedBy>MM-P-C6CFD7A2</LastUpdatedBy>
  <LastUpdateTimeStamp>2017-12-18T10:29:55.007</LastUpdateTimeStamp>
 </Rule>
 <Rule>
  <CountryOrganizationId>DE</CountryOrganizationId>
  <ItemId>2D7A7ACF-3914-2C87-0A32-1CDDB1974DED</ItemId>
  <Context>
   <OrganizationId>RS_DE_SV_ALLIANZ_ADMIN</OrganizationId>
  </Context>
  <RuleType>DataAccessRight</RuleType>
  <Key>TaskType.SEND</Key>
  <Value>{"AccessLevel":"SPECIFIC","AccessLevelParam":["ML-O-209801"]}</Value>
  <Status>Active</Status>
  <CreatedBy>MM-P-9BBB2219</CreatedBy>
  <CreationTimeStamp>2017-04-13T15:20:07.611</CreationTimeStamp>
  <LastUpdatedBy>MM-P-C6CFD7A2</LastUpdatedBy>
  <LastUpdateTimeStamp>2017-12-18T10:29:55.010</LastUpdateTimeStamp>
 </Rule>
 <Rule>
  <CountryOrganizationId>DE</CountryOrganizationId>
  <ItemId>B326A529-09FC-CDBB-A621-9ED9E8845BC0</ItemId>
  <Context>
   <Process>NO_PROCESS</Process>
   <ProcessStep>DashBoard</ProcessStep>
   <OrganizationId>RS_DE_SV_ALLIANZ_ADMIN</OrganizationId>
  </Context>
  <RuleType>Configuration</RuleType>
  <Key>headerTemplate</Key>
  <Value>MaterialDesign/MaterialDesignHeader.htm</Value>
  <Status>Active</Status>
  <CreatedBy>MM-P-9BBB2219</CreatedBy>
  <CreationTimeStamp>2017-04-13T15:20:07.703</CreationTimeStamp>
  <LastUpdatedBy>MM-P-C6CFD7A2</LastUpdatedBy>
  <LastUpdateTimeStamp>2017-11-14T09:28:17.528</LastUpdateTimeStamp>
 </Rule>
 <Rule>
  <CountryOrganizationId>DE</CountryOrganizationId>
  <ItemId>EFE4D626-9BEA-DAFB-8800-DB6242DA85F8</ItemId>
  <Context>
   <Process>MasterData</Process>
   <OrganizationId>RS_DE_SV_ALLIANZ_ADMIN</OrganizationId>
  </Context>
  <RuleType>Configuration</RuleType>
  <Key>toolbarTemplate</Key>
  <Value>MaterialDesign/MaterialDesignToolbar.htm</Value>
  <Status>Active</Status>
  <CreatedBy>MM-P-9BBB2219</CreatedBy>
  <CreationTimeStamp>2017-04-13T15:20:07.736</CreationTimeStamp>
  <LastUpdatedBy>MM-P-C6CFD7A2</LastUpdatedBy>
  <LastUpdateTimeStamp>2017-11-14T09:28:17.579</LastUpdateTimeStamp>
 </Rule>
 <Rule>
  <CountryOrganizationId>DE</CountryOrganizationId>
  <ItemId>ACF7E74D-EA42-CBF5-429F-1004244CE62F</ItemId>
  <Context>
   <Process>NO_PROCESS</Process>
   <ProcessStep>flsReassign</ProcessStep>
   <OrganizationId>RS_DE_SV_ALLIANZ_ADMIN</OrganizationId>
  </Context>
  <RuleType>FlowProcessorConfiguration</RuleType>
  <Key>ChangeTaskOwnerWorkflowFunction.FLSAssessorAssignmentNotificationTransformation(flsReassign2)</Key>
  <Value>{}</Value>
  <Status>Active</Status>
  <CreatedBy>MM-P-C6CFD7A2</CreatedBy>
  <CreationTimeStamp>2018-01-11T09:53:34.228</CreationTimeStamp>
  <LastUpdatedBy>MM-P-C6CFD7A2</LastUpdatedBy>
  <LastUpdateTimeStamp>2018-01-11T09:53:34.228</LastUpdateTimeStamp>
 </Rule>
 <Rule>
  <CountryOrganizationId>DE</CountryOrganizationId>
  <ItemId>7BB9EBD3-FC69-0EBE-4F15-B6633CFBCF4A</ItemId>
  <Context>
   <Process>NO_PROCESS</Process>
   <ProcessStep>flsDispatch</ProcessStep>
   <OrganizationId>RS_DE_SV_ALLIANZ_ADMIN</OrganizationId>
  </Context>
  <RuleType>FlowProcessorConfiguration</RuleType>
  <Key>ChangeTaskOwnerWorkflowFunction.KADFlsPrintTransformation(1511788174906)</Key>
  <Value>{typeOfReport: "DISPATCH", deleteOldReport: "true"}</Value>
  <Status>Active</Status>
  <CreatedBy>MM-P-C6CFD7A2</CreatedBy>
  <CreationTimeStamp>2018-01-11T10:01:35.012</CreationTimeStamp>
  <LastUpdatedBy>MM-P-C6CFD7A2</LastUpdatedBy>
  <LastUpdateTimeStamp>2018-01-11T10:01:35.012</LastUpdateTimeStamp>
 </Rule>
 <Rule>
  <CountryOrganizationId>DE</CountryOrganizationId>
  <ItemId>4CE88571-F498-EEC1-B223-5E71494C1E4F</ItemId>
  <Context>
   <Process>NO_PROCESS</Process>
   <ProcessStep>flsReassign</ProcessStep>
   <OrganizationId>RS_DE_SV_ALLIANZ_ADMIN</OrganizationId>
  </Context>
  <RuleType>FlowProcessorConfiguration</RuleType>
  <Key>ChangeTaskOwnerWorkflowFunction.KADFlsPrintTransformation(1511788174906)</Key>
  <Value>{typeOfReport: "DISPATCH", deleteOldReport: "true"}</Value>
  <Status>Active</Status>
  <CreatedBy>MM-P-C6CFD7A2</CreatedBy>
  <CreationTimeStamp>2018-01-12T15:55:40.904</CreationTimeStamp>
  <LastUpdatedBy>MM-P-C6CFD7A2</LastUpdatedBy>
  <LastUpdateTimeStamp>2018-01-12T15:55:40.904</LastUpdateTimeStamp>
 </Rule>
 <Rule>
  <CountryOrganizationId>DE</CountryOrganizationId>
  <ItemId>433045C0-E815-5F75-C70B-1EDD041A05C7</ItemId>
  <Context>
   <Process>NO_PROCESS</Process>
   <ProcessStep>MaterialGrid</ProcessStep>
   <OrganizationId>RS_DE_SV_ALLIANZ_ADMIN</OrganizationId>
  </Context>
  <RuleType>Configuration</RuleType>
  <Key>views</Key>
  <Value>worklistgrid_copied,worklistgrid_open,worklistgrid_sent,worklistgrid_closed,worklistgrid_deleted</Value>
  <Status>Active</Status>
  <CreatedBy>MM-P-C6CFD7A2</CreatedBy>
  <CreationTimeStamp>2018-01-22T09:27:49.295</CreationTimeStamp>
  <LastUpdatedBy>MM-P-C6CFD7A2</LastUpdatedBy>
  <LastUpdateTimeStamp>2018-01-22T09:27:49.295</LastUpdateTimeStamp>
 </Rule>
 <Rule>
  <CountryOrganizationId>DE</CountryOrganizationId>
  <ItemId>E918ABA6-B197-91C3-DC96-D11FCF349C8B</ItemId>
  <Context>
   <Process>NO_PROCESS</Process>
   <ProcessStep>flsReassign</ProcessStep>
   <OrganizationId>RS_DE_SV_ALLIANZ_ADMIN</OrganizationId>
  </Context>
  <RuleType>FlowProcessorConfiguration</RuleType>
  <Key>SendTask.FLSNotificationPostAction(flsReassign)</Key>
  <Value>{errorNotificationEMAILAddress:"michel.varga@ax-ao.de"}</Value>
  <Status>Active</Status>
  <CreatedBy>MM-P-C6CFD7A2</CreatedBy>
  <CreationTimeStamp>2018-01-11T09:52:16.912</CreationTimeStamp>
  <LastUpdatedBy>MM-P-C6CFD7A2</LastUpdatedBy>
  <LastUpdateTimeStamp>2018-01-15T13:23:11.161</LastUpdateTimeStamp>
 </Rule>
 <Size>63</Size>
</BRERuleListType>
